Metadata-Version: 1.0
Name: slack-archiver
Version: 0.0.2
Summary: Archives slack channels
Home-page: UNKNOWN
Author: Mike Bryant
Author-email: mike.bryant@ocado.com
License: UNKNOWN
Platform: UNKNOWN
